lyrica/AZLyricsSession.py
lyrica/GeniusSession.py
lyrica/Lyrica.py
lyrica/SiteSession.py
lyrica/__init__.py
lyrica/bin.py
lyrica/utils.py
lyrica-1.3.4.dist-info/METADATA
lyrica-1.3.4.dist-info/RECORD
lyrica-1.3.4.dist-info/WHEEL
lyrica-1.3.4.dist-info/entry_points.txt
lyrica-1.3.4.dist-info/top_level.txt
